nuacht/__init__.py
nuacht/nuacht.py
nuacht-0.2.2.dist-info/licenses/LICENCE
nuacht-0.2.2.dist-info/METADATA
nuacht-0.2.2.dist-info/WHEEL
nuacht-0.2.2.dist-info/top_level.txt
nuacht-0.2.2.dist-info/RECORD
