Metadata-Version: 2.4
Name: nuacht
Version: 0.2.2
Summary: Grabs entries from RSS feeds and stores in a database.
Author-email: Riain Ó Tuathail <rotuathail01@gmail.com>
License-Expression: MIT
Classifier: Programming Language :: Python :: 3
Classifier: Operating System :: OS Independent
Requires-Python: >=3.9
License-File: LICENCE
Requires-Dist: feedparser==6.0.12
Requires-Dist: PyYAML==6.0.3
Dynamic: license-file
